nl_opendata_mcp/__init__.py
nl_opendata_mcp/config.py
nl_opendata_mcp/server.py
nl_opendata_mcp/models/__init__.py
nl_opendata_mcp/models/inputs.py
nl_opendata_mcp/services/__init__.py
nl_opendata_mcp/services/cache.py
nl_opendata_mcp/services/http_client.py
nl_opendata_mcp/services/translator.py
nl_opendata_mcp/tools/__init__.py
nl_opendata_mcp/tools/analysis.py
nl_opendata_mcp/tools/base.py
nl_opendata_mcp/tools/discovery.py
nl_opendata_mcp/tools/export.py
nl_opendata_mcp/tools/metadata.py
nl_opendata_mcp/tools/query.py
nl_opendata_mcp/utils/__init__.py
nl_opendata_mcp/utils/errors.py
nl_opendata_mcp/utils/security.py
nl_opendata_mcp-1.0.4.dist-info/METADATA
nl_opendata_mcp-1.0.4.dist-info/WHEEL
nl_opendata_mcp-1.0.4.dist-info/entry_points.txt
nl_opendata_mcp-1.0.4.dist-info/licenses/LICENSE
nl_opendata_mcp-1.0.4.dist-info/RECORD
