Metadata-Version: 2.4
Name: nl-opendata-mcp
Version: 1.0.4
Summary: MCP Server for Dutch government open data (CBS, data.overheid.nl)
Project-URL: Repository, https://github.com/soulnai/nl-opendata-mcp
Project-URL: Homepage, https://github.com/soulnai/nl-opendata-mcp
Author-email: Oleksandr <oleksandr.vasyliev@proton.me>
License: MIT License
License-File: LICENSE
Keywords: ai,cbs,llm,mcp,netherlands,opendata
Classifier: Development Status :: 4 - Beta
Classifier: Intended Audience :: Developers
Classifier: License :: OSI Approved :: MIT License
Classifier: Programming Language :: Python :: 3
Classifier: Programming Language :: Python :: 3.10
Classifier: Programming Language :: Python :: 3.11
Classifier: Programming Language :: Python :: 3.12
Requires-Python: >=3.10
Requires-Dist: duckdb
Requires-Dist: fastmcp>=2.13.2
Requires-Dist: httpx[http2]>=0.28.1
Requires-Dist: pandas
Requires-Dist: pydantic-settings>=2.0.0
Requires-Dist: pydantic>=2.12.5
Requires-Dist: seaborn>=0.13.2
